_wallycore.cpython-310-aarch64-linux-gnu.so
wallycore/__init__.py
wallycore-1.5.1.dist-info/METADATA
wallycore-1.5.1.dist-info/WHEEL
wallycore-1.5.1.dist-info/top_level.txt
wallycore-1.5.1.dist-info/RECORD
wallycore-1.5.1.dist-info/licenses/LICENSE
