Metadata-Version: 2.4
Name: wallycore
Version: 1.5.1
Summary: libwally Bitcoin library
Home-page: https://github.com/ElementsProject/libwally-core
Author: Jon Griffiths
Author-email: jon_p_griffiths@yahoo.com
License: MIT
Project-URL: Documentation, https://wally.readthedocs.io/en/latest
Project-URL: Source, https://github.com/ElementsProject/libwally-core
Project-URL: Tracker, https://github.com/ElementsProject/libwally-core/issues
Keywords: Bitcoin,wallet,BIP32,BIP38,BIP39,secp256k1,Blockstream,Liquid,Elements
Classifier: Development Status :: 5 - Production/Stable
Classifier: Intended Audience :: Developers
Classifier: Topic :: Software Development :: Libraries
Classifier: License :: OSI Approved :: MIT License
Classifier: Programming Language :: Python :: 3
License-File: LICENSE
Dynamic: author
Dynamic: author-email
Dynamic: classifier
Dynamic: description
Dynamic: home-page
Dynamic: keywords
Dynamic: license
Dynamic: license-file
Dynamic: project-url
Dynamic: summary
